backtracking/__init__.py
backtracking/src/__init__.py
backtracking/src/core.py
examples/n_queens.py
backtracking-0.1.2.dist-info/LICENSE
backtracking-0.1.2.dist-info/METADATA
backtracking-0.1.2.dist-info/WHEEL
backtracking-0.1.2.dist-info/top_level.txt
backtracking-0.1.2.dist-info/RECORD
