Metadata-Version: 2.1
Name: backtracking
Version: 0.1.2
Summary: A framework for backtracking algorithm, as an interface and a solving function.
Home-page: https://github.com/tboulet/backtracking_algorithm
Author: tboulet
Author-email: timothe.boulet0@gmail.com
License: MIT
License-File: LICENSE
